remax_pipeline/__init__.py
remax_pipeline/_version.py
remax_pipeline/celery.py
remax_pipeline/pipeline.py
remax_pipeline/config/__init__.py
remax_pipeline/config/settings.py
remax_pipeline/db/__init__.py
remax_pipeline/db/db.py
remax_pipeline/db/decorators/__init__.py
remax_pipeline/db/decorators/connector.py
remax_pipeline/models/__init__.py
remax_pipeline/models/listing.py
remax_pipeline/models/pipeline_runs.py
remax_pipeline/pipe/__init__.py
remax_pipeline/pipe/extract.py
remax_pipeline/pipe/load.py
remax_pipeline/pipe/validate.py
remax_pipeline/plugins/__init__.py
remax_pipeline/plugins/web_crawler.py
remax_pipeline/services/__init__.py
remax_pipeline/services/aws_secrets_service.py
remax_pipeline/services/fileio_service.py
remax_pipeline/services/misc_service.py
remax_pipeline/services/selenium_service.py
remax_pipeline/services/sql_service.py
remax_pipeline/tasks/__init__.py
remax_pipeline/tasks/etl_task.py
remax_pipeline/utils/__init__.py
remax_pipeline/utils/logging.py
remax_pipeline-0.2.4.dist-info/LICENSE
remax_pipeline-0.2.4.dist-info/METADATA
remax_pipeline-0.2.4.dist-info/WHEEL
remax_pipeline-0.2.4.dist-info/top_level.txt
remax_pipeline-0.2.4.dist-info/RECORD
